Workbook

Sheet Sheet1
A1: Cropland | B1: Acres | C1: 27903626 | G1: Acre per farm | H1: =C1/C2 -> 238.52107
B2: Number of Operations | C2: 116986 | G2: Sales per acre | H2: =C20/C1 -> 259.7027
A3: Cropland (excl Harvested & Pastured) | B3: Acres | C3: 12701877
B4: Number of Operations | C4: 46675
A5: All crops failed | B5: Acres | C5: 7351748
B6: Number of Operations | C6: 18551
A7: Cultivated Summer Fallow | B7: Acres | C7: 1451257
B8: Number of Operations | C8: 11492
A9: Idle | B9: Acres | C9: 3898872
B10: Number of Operations | C10: 23723
A11: Harvested | B11: Acres | C11: 12467602
B12: Number of Operations | C12: 81443
A13: Pastured | B13: Acres | C13: 2734147
B14: Number of Operations | C14: 16101
A20: Cropland | B20: Total Sales | C20: 7246647000

Sheet Texas Acres
A1: AG LAND, CROPLAND - ACRES | B1: NAICS CLASSIFICATION: (1111) | C1: 6571967 | E1: =C1/C32 -> 1284.842
A2: AG LAND, CROPLAND - ACRES | B2: NAICS CLASSIFICATION: (1112) | C2: 492463 | E2: =C2/C33 -> 327.65336
A3: AG LAND, CROPLAND - ACRES | B3: NAICS CLASSIFICATION: (1113) | C3: 265150 | D3: =SUM(C1:C3) -> 7329580 | E3: =C3/C34 -> 45.762858
A4: AG LAND, CROPLAND - ACRES | B4: NAICS CLASSIFICATION: (1114) | C4: 130914 | D4: =SUM(C1:C4) -> 7460494 | E4: =C4/C35 -> 79.438107
A5: AG LAND, CROPLAND - ACRES | B5: NAICS CLASSIFICATION: (1119) | C5: 12134458 | D5: =SUM(C1:C5) -> 19594952 | E5: =C5/C36 -> 269.92455
A6: AG LAND, CROPLAND, (EXCL HARVESTED & PASTURED), ALL CROPS FAILED - ACRES | B6: NAICS CLASSIFICATION: (1111) | C6: 1257216
A7: AG LAND, CROPLAND, (EXCL HARVESTED & PASTURED), ALL CROPS FAILED - ACRES | B7: NAICS CLASSIFICATION: (1112) | C7: 159444
A8: AG LAND, CROPLAND, (EXCL HARVESTED & PASTURED), ALL CROPS FAILED - ACRES | B8: NAICS CLASSIFICATION: (1113) | C8: 51530
A9: AG LAND, CROPLAND, (EXCL HARVESTED & PASTURED), ALL CROPS FAILED - ACRES | B9: NAICS CLASSIFICATION: (1114) | C9: 6522
A10: AG LAND, CROPLAND, (EXCL HARVESTED & PASTURED), ALL CROPS FAILED - ACRES | B10: NAICS CLASSIFICATION: (1119) | C10: 4050148 | E10: =SUM(C6:C10) -> 5524860
A11: AG LAND, CROPLAND, (EXCL HARVESTED & PASTURED), CULTIVATED SUMMER FALLOW - ACRES | B11: NAICS CLASSIFICATION: (1111) | C11: 324718
A12: AG LAND, CROPLAND, (EXCL HARVESTED & PASTURED), CULTIVATED SUMMER FALLOW - ACRES | B12: NAICS CLASSIFICATION: (1112) | C12: 12475
A13: AG LAND, CROPLAND, (EXCL HARVESTED & PASTURED), CULTIVATED SUMMER FALLOW - ACRES | B13: NAICS CLASSIFICATION: (1113) | C13: 14843
A14: AG LAND, CROPLAND, (EXCL HARVESTED & PASTURED), CULTIVATED SUMMER FALLOW - ACRES | B14: NAICS CLASSIFICATION: (1114) | C14: 8281
A15: AG LAND, CROPLAND, (EXCL HARVESTED & PASTURED), CULTIVATED SUMMER FALLOW - ACRES | B15: NAICS CLASSIFICATION: (1119) | C15: 506691 | E15: =SUM(C11:C15) -> 867008
A16: AG LAND, CROPLAND, (EXCL HARVESTED & PASTURED), IDLE - ACRES | B16: NAICS CLASSIFICATION: (1111) | C16: 438966
A17: AG LAND, CROPLAND, (EXCL HARVESTED & PASTURED), IDLE - ACRES | B17: NAICS CLASSIFICATION: (1112) | C17: 84049
A18: AG LAND, CROPLAND, (EXCL HARVESTED & PASTURED), IDLE - ACRES | B18: NAICS CLASSIFICATION: (1113) | C18: 31510
A19: AG LAND, CROPLAND, (EXCL HARVESTED & PASTURED), IDLE - ACRES | B19: NAICS CLASSIFICATION: (1114) | C19: 15350
A20: AG LAND, CROPLAND, (EXCL HARVESTED & PASTURED), IDLE - ACRES | B20: NAICS CLASSIFICATION: (1119) | C20: 2399629 | E20: =SUM(C16:C20) -> 2969504
A21: AG LAND, CROPLAND, HARVESTED - ACRES | B21: NAICS CLASSIFICATION: (1111) | C21: 4303703
A22: AG LAND, CROPLAND, HARVESTED - ACRES | B22: NAICS CLASSIFICATION: (1112) | C22: 211000
A23: AG LAND, CROPLAND, HARVESTED - ACRES | B23: NAICS CLASSIFICATION: (1113) | C23: 156652
A24: AG LAND, CROPLAND, HARVESTED - ACRES | B24: NAICS CLASSIFICATION: (1114) | C24: 97247
A25: AG LAND, CROPLAND, HARVESTED - ACRES | B25: NAICS CLASSIFICATION: (1119) | C25: 4695075 | E25: =SUM(C21:C25) -> 9463677
A26: AG LAND, CROPLAND, PASTURED ONLY - ACRES | B26: NAICS CLASSIFICATION: (1111) | C26: 247364
A27: AG LAND, CROPLAND, PASTURED ONLY - ACRES | B27: NAICS CLASSIFICATION: (1112) | C27: 25495
A28: AG LAND, CROPLAND, PASTURED ONLY - ACRES | B28: NAICS CLASSIFICATION: (1113) | C28: 10615
A29: AG LAND, CROPLAND, PASTURED ONLY - ACRES | B29: NAICS CLASSIFICATION: (1114) | C29: 3514
A30: AG LAND, CROPLAND, PASTURED ONLY - ACRES | B30: NAICS CLASSIFICATION: (1119) | C30: 482915 | E30: =SUM(C26:C30) -> 769903
A32: AG LAND, CROPLAND - NUMBER OF OPERATIONS | B32: NAICS CLASSIFICATION: (1111) | C32: 5115
A33: AG LAND, CROPLAND - NUMBER OF OPERATIONS | B33: NAICS CLASSIFICATION: (1112) | C33: 1503
A34: AG LAND, CROPLAND - NUMBER OF OPERATIONS | B34: NAICS CLASSIFICATION: (1113) | C34: 5794 | E34: =SUM(C32:C34) -> 12412
A35: AG LAND, CROPLAND - NUMBER OF OPERATIONS | B35: NAICS CLASSIFICATION: (1114) | C35: 1648 | E35: =SUM(C32:C35) -> 14060
A36: AG LAND, CROPLAND - NUMBER OF OPERATIONS | B36: NAICS CLASSIFICATION: (1119) | C36: 44955 | E36: =SUM(C32:C36) -> 59015
A37: AG LAND, CROPLAND, (EXCL HARVESTED & PASTURED), ALL CROPS FAILED - NUMBER OF OPERATIONS | B37: NAICS CLASSIFICATION: (1111) | C37: 1278
A38: AG LAND, CROPLAND, (EXCL HARVESTED & PASTURED), ALL CROPS FAILED - NUMBER OF OPERATIONS | B38: NAICS CLASSIFICATION: (1112) | C38: 248
A39: AG LAND, CROPLAND, (EXCL HARVESTED & PASTURED), ALL CROPS FAILED - NUMBER OF OPERATIONS | B39: NAICS CLASSIFICATION: (1113) | C39: 609
A40: AG LAND, CROPLAND, (EXCL HARVESTED & PASTURED), ALL CROPS FAILED - NUMBER OF OPERATIONS | B40: NAICS CLASSIFICATION: (1114) | C40: 115
A41: AG LAND, CROPLAND, (EXCL HARVESTED & PASTURED), ALL CROPS FAILED - NUMBER OF OPERATIONS | B41: NAICS CLASSIFICATION: (1119) | C41: 8062 | E41: =SUM(C37:C41) -> 10312
A42: AG LAND, CROPLAND, (EXCL HARVESTED & PASTURED), CULTIVATED SUMMER FALLOW - NUMBER OF OPERATIONS | B42: NAICS CLASSIFICATION: (1111) | C42: 775
A43: AG LAND, CROPLAND, (EXCL HARVESTED & PASTURED), CULTIVATED SUMMER FALLOW - NUMBER OF OPERATIONS | B43: NAICS CLASSIFICATION: (1112) | C43: 189
A44: AG LAND, CROPLAND, (EXCL HARVESTED & PASTURED), CULTIVATED SUMMER FALLOW - NUMBER OF OPERATIONS | B44: NAICS CLASSIFICATION: (1113) | C44: 336
A45: AG LAND, CROPLAND, (EXCL HARVESTED & PASTURED), CULTIVATED SUMMER FALLOW - NUMBER OF OPERATIONS | B45: NAICS CLASSIFICATION: (1114) | C45: 92
A46: AG LAND, CROPLAND, (EXCL HARVESTED & PASTURED), CULTIVATED SUMMER FALLOW - NUMBER OF OPERATIONS | B46: NAICS CLASSIFICATION: (1119) | C46: 3903 | E46: =SUM(C42:C46) -> 5295
A47: AG LAND, CROPLAND, (EXCL HARVESTED & PASTURED), IDLE - NUMBER OF OPERATIONS | B47: NAICS CLASSIFICATION: (1111) | C47: 925
A48: AG LAND, CROPLAND, (EXCL HARVESTED & PASTURED), IDLE - NUMBER OF OPERATIONS | B48: NAICS CLASSIFICATION: (1112) | C48: 265
A49: AG LAND, CROPLAND, (EXCL HARVESTED & PASTURED), IDLE - NUMBER OF OPERATIONS | B49: NAICS CLASSIFICATION: (1113) | C49: 764
A50: AG LAND, CROPLAND, (EXCL HARVESTED & PASTURED), IDLE - NUMBER OF OPERATIONS | B50: NAICS CLASSIFICATION: (1114) | C50: 222
A51: AG LAND, CROPLAND, (EXCL HARVESTED & PASTURED), IDLE - NUMBER OF OPERATIONS | B51: NAICS CLASSIFICATION: (1119) | C51: 12177 | E51: =SUM(C47:C51) -> 14353
A52: AG LAND, CROPLAND, HARVESTED - NUMBER OF OPERATIONS | B52: NAICS CLASSIFICATION: (1111) | C52: 5115
A53: AG LAND, CROPLAND, HARVESTED - NUMBER OF OPERATIONS | B53: NAICS CLASSIFICATION: (1112) | C53: 1503
A54: AG LAND, CROPLAND, HARVESTED - NUMBER OF OPERATIONS | B54: NAICS CLASSIFICATION: (1113) | C54: 5794
A55: AG LAND, CROPLAND, HARVESTED - NUMBER OF OPERATIONS | B55: NAICS CLASSIFICATION: (1114) | C55: 1648
A56: AG LAND, CROPLAND, HARVESTED - NUMBER OF OPERATIONS | B56: NAICS CLASSIFICATION: (1119) | C56: 28993 | E56: =SUM(C52:C56) -> 43053
A57: AG LAND, CROPLAND, PASTURED ONLY - NUMBER OF OPERATIONS | B57: NAICS CLASSIFICATION: (1111) | C57: 364
A58: AG LAND, CROPLAND, PASTURED ONLY - NUMBER OF OPERATIONS | B58: NAICS CLASSIFICATION: (1112) | C58: 120
A59: AG LAND, CROPLAND, PASTURED ONLY - NUMBER OF OPERATIONS | B59: NAICS CLASSIFICATION: (1113) | C59: 361
A60: AG LAND, CROPLAND, PASTURED ONLY - NUMBER OF OPERATIONS | B60: NAICS CLASSIFICATION: (1114) | C60: 106
A61: AG LAND, CROPLAND, PASTURED ONLY - NUMBER OF OPERATIONS | B61: NAICS CLASSIFICATION: (1119) | C61: 2288 | E61: =SUM(C57:C61) -> 3239
A63: Acre per farm | B63: =D5/E36 -> 332.03342 | C63: =B63/2.47105 -> 134.36936
A64: Acre per farm (excl: 1119) | B64: =D4/E35 -> 530.61835 | C64: =B64/2.47105 -> 214.73396
A65: Acre per farm (excl: 1114 and 1119) | B65: =D3/E34 -> 590.52369 | C65: =B65/2.47105 -> 238.97683
A66: Acre per farm 1119 | B66: =C5/C36 -> 269.92455 | C66: =B66/2.47105 -> 109.23476
A67: Acre per farm 1111 and 1112 | B67: =(C1+C2)/(C32+C33) -> 1067.4569 | C67: =B67/2.47105 -> 431.98516
A68: Acre per farm 1111 | B68: =C1/C32 -> 1284.842 | C68: =B68/2.47105 -> 519.95793
A69: Acre per farm 1112 | B69: =C2/C33 -> 327.65336 | C69: =B69/2.47105 -> 132.59682

Sheet National Acres
A1: AG LAND, CROPLAND - ACRES | B1: NAICS CLASSIFICATION | C1: NAICS CLASSIFICATION: (1111) | D1: 235703790
A2: AG LAND, CROPLAND - ACRES | B2: NAICS CLASSIFICATION | C2: NAICS CLASSIFICATION: (1112) | D2: 7275938
A3: AG LAND, CROPLAND - ACRES | B3: NAICS CLASSIFICATION | C3: NAICS CLASSIFICATION: (1113) | D3: 7631889
A4: AG LAND, CROPLAND - ACRES | B4: NAICS CLASSIFICATION | C4: NAICS CLASSIFICATION: (1114) | D4: 1788459
A5: AG LAND, CROPLAND - ACRES | B5: NAICS CLASSIFICATION | C5: NAICS CLASSIFICATION: (1119) | D5: 61215533 | E5: =SUM(D1:D5) -> 313615609
A6: AG LAND, CROPLAND - NUMBER OF OPERATIONS | B6: NAICS CLASSIFICATION | C6: NAICS CLASSIFICATION: (1111) | D6: 330930
A7: AG LAND, CROPLAND - NUMBER OF OPERATIONS | B7: NAICS CLASSIFICATION | C7: NAICS CLASSIFICATION: (1112) | D7: 41793
A8: AG LAND, CROPLAND - NUMBER OF OPERATIONS | B8: NAICS CLASSIFICATION | C8: NAICS CLASSIFICATION: (1113) | D8: 97343
A9: AG LAND, CROPLAND - NUMBER OF OPERATIONS | B9: NAICS CLASSIFICATION | C9: NAICS CLASSIFICATION: (1114) | D9: 50782
A10: AG LAND, CROPLAND - NUMBER OF OPERATIONS | B10: NAICS CLASSIFICATION | C10: NAICS CLASSIFICATION: (1119) | D10: 418301 | E10: =SUM(D6:D10) -> 939149
A12: Acre per farm | B12: =E5/E10 -> 333.93595

Sheet Net Cash Income
A1: Texas | D1: per acre
A2: INCOME, NET CASH FARM, OF OPERATIONS - NET INCOME, MEASURED IN $ | B2: NAICS CLASSIFICATION: (1111) | C2: 771430000 | D2: =C2/'Texas Acres'!C1 -> 117.3819
A3: INCOME, NET CASH FARM, OF OPERATIONS - NET INCOME, MEASURED IN $ | B3: NAICS CLASSIFICATION: (1112) | C3: 184060000 | D3: =C3/'Texas Acres'!C2 -> 373.75397
A4: INCOME, NET CASH FARM, OF OPERATIONS - NET INCOME, MEASURED IN $ | B4: NAICS CLASSIFICATION: (1113) | C4: 18064000 | D4: =C4/'Texas Acres'!C3 -> 68.127475 | E4: =SUM(C2:C4) -> 973554000
A5: INCOME, NET CASH FARM, OF OPERATIONS - NET INCOME, MEASURED IN $ | B5: NAICS CLASSIFICATION: (1114) | C5: 439527000 | D5: =C5/'Texas Acres'!C4 -> 3357.372 | E5: =SUM(C2:C5) -> 1413081000
A6: INCOME, NET CASH FARM, OF OPERATIONS - NET INCOME, MEASURED IN $ | B6: NAICS CLASSIFICATION: (1119) | C6: 548390000 | D6: =C6/'Texas Acres'!C5 -> 45.192789 | E6: =SUM(C2:C6) -> 1961471000
A7: Total
G8: 1119 | H8: 1111+1112 | I8: 1111 | J8: 1112
A9: Income per acre | C9: =E6/'Texas Acres'!D5 -> 100.10083 | D9: =E5/'Texas Acres'!D4 -> 189.4085 | E9: =E4/'Texas Acres'!D3 -> 132.82535 | G9: =C6/'Texas Acres'!C5 -> 45.192789 | H9: =(C2+C3)/('Texas Acres'!C1+'Texas Acres'!C2) -> 135.25366 | I9: =D2 -> 117.3819 | J9: =D3 -> 373.75397
A10: Income per farm | C10: =E6/'Texas Acres'!E36 -> 33236.821 | D10: =E5/'Texas Acres'!E35 -> 100503.63 | E10: =E4/'Texas Acres'!E34 -> 78436.513 | G10: =C6/'Texas Acres'!C36 -> 12198.643 | H10: =(C2+C3)/('Texas Acres'!C32+'Texas Acres'!C33) -> 144377.46 | I10: =C2/'Texas Acres'!C32 -> 150817.2 | J10: =C3/'Texas Acres'!C33 -> 122461.74
A13: Conventional crop farming excluding fertilizer expenses | C13: Net income | D13: Expenses fertilizer | E13: Total
A14: INCOME, NET CASH FARM, OF OPERATIONS - NET INCOME, MEASURED IN $ | B14: NAICS CLASSIFICATION: (1111) | C14: 771430000 | D14: 466451000 | E14: =C14+D14 -> 1237881000
A15: INCOME, NET CASH FARM, OF OPERATIONS - NET INCOME, MEASURED IN $ | B15: NAICS CLASSIFICATION: (1112) | C15: 184060000 | D15: 64500000 | E15: =C15+D15 -> 248560000
A16: INCOME, NET CASH FARM, OF OPERATIONS - NET INCOME, MEASURED IN $ | B16: NAICS CLASSIFICATION: (1113) | C16: 18064000 | D16: 22845000 | E16: =C16+D16 -> 40909000
A17: INCOME, NET CASH FARM, OF OPERATIONS - NET INCOME, MEASURED IN $ | B17: NAICS CLASSIFICATION: (1114) | C17: 439527000 | D17: 56284000 | E17: =C17+D17 -> 495811000
A18: INCOME, NET CASH FARM, OF OPERATIONS - NET INCOME, MEASURED IN $ | B18: NAICS CLASSIFICATION: (1119) | C18: 548390000 | D18: 409958000 | E18: =C18+D18 -> 958348000
A19: Total | C19: =SUM(C14:C18) -> 1961471000 | D19: =SUM(D14:D18) -> 1020038000 | E19: =SUM(E14:E18) -> 2981509000
A21: Income per acre | C21: =C19/'Texas Acres'!D5 -> 100.10083 | D21: =D19/'Texas Acres'!D5 -> 52.056162 | E21: =E19/'Texas Acres'!D5 -> 152.15699
A22: Income per farm | C22: =C19/'Texas Acres'!E36 -> 33236.821 | E22: =E19/'Texas Acres'!E36 -> 50521.206
A27: USA
A28: INCOME, NET CASH FARM, OF OPERATIONS - NET INCOME, MEASURED IN $ | B28: NAICS CLASSIFICATION: (1111) | C28: 56880196000
A29: INCOME, NET CASH FARM, OF OPERATIONS - NET INCOME, MEASURED IN $ | B29: NAICS CLASSIFICATION: (1112) | C29: 7703300000
A30: INCOME, NET CASH FARM, OF OPERATIONS - NET INCOME, MEASURED IN $ | B30: NAICS CLASSIFICATION: (1113) | C30: 5822093000
A31: INCOME, NET CASH FARM, OF OPERATIONS - NET INCOME, MEASURED IN $ | B31: NAICS CLASSIFICATION: (1114) | C31: 5470565000
A32: INCOME, NET CASH FARM, OF OPERATIONS - NET INCOME, MEASURED IN $ | B32: NAICS CLASSIFICATION: (1119) | C32: 7935805000
A33: Total | C33: =SUM(C28:C32) -> 83811959000
A35: Income per acre | C35: =C33/'National Acres'!E5 -> 267.24422
A36: Income per farm | C36: =C33/'National Acres'!E10 -> 89242.451

Sheet Income
A1: INCOME, FARM-RELATED - RECEIPTS, MEASURED IN $ | B1: NAICS CLASSIFICATION: (1111) | C1: 296224000
A2: INCOME, FARM-RELATED - RECEIPTS, MEASURED IN $ | B2: NAICS CLASSIFICATION: (1112) | C2: 35570000
A3: INCOME, FARM-RELATED - RECEIPTS, MEASURED IN $ | B3: NAICS CLASSIFICATION: (1113) | C3: 54529000
A4: INCOME, FARM-RELATED - RECEIPTS, MEASURED IN $ | B4: NAICS CLASSIFICATION: (1114) | C4: 19958000
A5: INCOME, FARM-RELATED - RECEIPTS, MEASURED IN $ | B5: NAICS CLASSIFICATION: (1119) | C5: 724025000
A6: Total | C6: =SUM(C1:C5) -> 1130306000
A8: Income per acre | C8: =C6/'Texas Acres'!D5 -> 57.68353
A9: Income per farm | C9: =C6/'Texas Acres'!E36 -> 19152.859
A14: INCOME, FARM-RELATED, AG SERVICES, CUSTOMWORK & OTHER - RECEIPTS, MEASURED IN $ | B14: NAICS CLASSIFICATION: (1111) | C14: 28762000
A15: INCOME, FARM-RELATED, AG SERVICES, CUSTOMWORK & OTHER - RECEIPTS, MEASURED IN $ | B15: NAICS CLASSIFICATION: (1112) | C15: 1748000
A16: INCOME, FARM-RELATED, AG SERVICES, CUSTOMWORK & OTHER - RECEIPTS, MEASURED IN $ | B16: NAICS CLASSIFICATION: (1113) | C16: 969000
A17: INCOME, FARM-RELATED, AG SERVICES, CUSTOMWORK & OTHER - RECEIPTS, MEASURED IN $ | B17: NAICS CLASSIFICATION: (1114) | C17: 1564000
A18: INCOME, FARM-RELATED, AG SERVICES, CUSTOMWORK & OTHER - RECEIPTS, MEASURED IN $ | B18: NAICS CLASSIFICATION: (1119) | C18: 50555000
A19: INCOME, FARM-RELATED, AG TOURISM & RECREATIONAL SERVICES - RECEIPTS, MEASURED IN $ | B19: NAICS CLASSIFICATION: (1111) | C19: 2011000
A20: INCOME, FARM-RELATED, AG TOURISM & RECREATIONAL SERVICES - RECEIPTS, MEASURED IN $ | B20: NAICS CLASSIFICATION: (1112) | C20: 265000
A21: INCOME, FARM-RELATED, AG TOURISM & RECREATIONAL SERVICES - RECEIPTS, MEASURED IN $ | B21: NAICS CLASSIFICATION: (1113) | C21: 9243000
A22: INCOME, FARM-RELATED, AG TOURISM & RECREATIONAL SERVICES - RECEIPTS, MEASURED IN $ | B22: NAICS CLASSIFICATION: (1114) | C22: 9175000
A23: INCOME, FARM-RELATED, AG TOURISM & RECREATIONAL SERVICES - RECEIPTS, MEASURED IN $ | B23: NAICS CLASSIFICATION: (1119) | C23: 18962000
A24: INCOME, FARM-RELATED, CROP & ANIMAL INSURANCE PAYMENTS - RECEIPTS, MEASURED IN $ | B24: NAICS CLASSIFICATION: (1111) | C24: 221347000
A25: INCOME, FARM-RELATED, CROP & ANIMAL INSURANCE PAYMENTS - RECEIPTS, MEASURED IN $ | B25: NAICS CLASSIFICATION: (1112) | C25: 28222000
... A53: INCOME, FARM-RELATED, RENT, LAND & BUILDINGS - RECEIPTS, MEASURED IN $ | B53: NAICS CLASSIFICATION: (1119) | C53: 130851000

Sheet Sales
A1: CROP TOTALS - SALES, MEASURED IN $ | B1: NAICS CLASSIFICATION: (1111) | C1: 2516499000
A2: CROP TOTALS - SALES, MEASURED IN $ | B2: NAICS CLASSIFICATION: (1112) | C2: 664547000
A3: CROP TOTALS - SALES, MEASURED IN $ | B3: NAICS CLASSIFICATION: (1113) | C3: 201713000
A4: CROP TOTALS - SALES, MEASURED IN $ | B4: NAICS CLASSIFICATION: (1114) | C4: 1169400000
A5: CROP TOTALS - SALES, MEASURED IN $ | B5: NAICS CLASSIFICATION: (1119) | C5: 2356172000
A6: Total | C6: =SUM(C1:C5) -> 6908331000
A8: Sales per acre | C8: =C6/'Texas Acres'!D5 -> 352.55667

Sheet Expenses
A1: AG SERVICES, CUSTOM SERVICES FOR LIVESTOCK, INCL MEDICAL SUPPLIES & VETERINARY - EXPENSE, MEASURED IN $ | B1: NAICS CLASSIFICATION: (1111) | C1: 4856000
A2: AG SERVICES, CUSTOM SERVICES FOR LIVESTOCK, INCL MEDICAL SUPPLIES & VETERINARY - EXPENSE, MEASURED IN $ | B2: NAICS CLASSIFICATION: (1112) | C2: 386000
A3: AG SERVICES, CUSTOM SERVICES FOR LIVESTOCK, INCL MEDICAL SUPPLIES & VETERINARY - EXPENSE, MEASURED IN $ | B3: NAICS CLASSIFICATION: (1113) | C3: 891000
A4: AG SERVICES, CUSTOM SERVICES FOR LIVESTOCK, INCL MEDICAL SUPPLIES & VETERINARY - EXPENSE, MEASURED IN $ | B4: NAICS CLASSIFICATION: (1114) | C4: 248000
A5: AG SERVICES, CUSTOM SERVICES FOR LIVESTOCK, INCL MEDICAL SUPPLIES & VETERINARY - EXPENSE, MEASURED IN $ | B5: NAICS CLASSIFICATION: (1119) | C5: 15710000 | D5: =SUM(C1:C5) -> 22091000
A6: AG SERVICES, CUSTOMWORK - EXPENSE, MEASURED IN $ | B6: NAICS CLASSIFICATION: (1111) | C6: 102053000
A7: AG SERVICES, CUSTOMWORK - EXPENSE, MEASURED IN $ | B7: NAICS CLASSIFICATION: (1112) | C7: 14683000
A8: AG SERVICES, CUSTOMWORK - EXPENSE, MEASURED IN $ | B8: NAICS CLASSIFICATION: (1113) | C8: 7415000
A9: AG SERVICES, CUSTOMWORK - EXPENSE, MEASURED IN $ | B9: NAICS CLASSIFICATION: (1114) | C9: 8452000
A10: AG SERVICES, CUSTOMWORK - EXPENSE, MEASURED IN $ | B10: NAICS CLASSIFICATION: (1119) | C10: 96302000 | D10: =SUM(C6:C10) -> 228905000
A11: AG SERVICES, MACHINERY RENTAL - EXPENSE, MEASURED IN $ | B11: NAICS CLASSIFICATION: (1111) | C11: 27671000
A12: AG SERVICES, MACHINERY RENTAL - EXPENSE, MEASURED IN $ | B12: NAICS CLASSIFICATION: (1112) | C12: 4191000
A13: AG SERVICES, MACHINERY RENTAL - EXPENSE, MEASURED IN $ | B13: NAICS CLASSIFICATION: (1113) | C13: 2785000
A14: AG SERVICES, MACHINERY RENTAL - EXPENSE, MEASURED IN $ | B14: NAICS CLASSIFICATION: (1114) | C14: 8989000
A15: AG SERVICES, MACHINERY RENTAL - EXPENSE, MEASURED IN $ | B15: NAICS CLASSIFICATION: (1119) | C15: 38751000 | D15: =SUM(C11:C15) -> 82387000
A16: AG SERVICES, OTHER - EXPENSE, MEASURED IN $ | B16: NAICS CLASSIFICATION: (1111) | C16: 124864000
A17: AG SERVICES, OTHER - EXPENSE, MEASURED IN $ | B17: NAICS CLASSIFICATION: (1112) | C17: 34810000
A18: AG SERVICES, OTHER - EXPENSE, MEASURED IN $ | B18: NAICS CLASSIFICATION: (1113) | C18: 23418000
A19: AG SERVICES, OTHER - EXPENSE, MEASURED IN $ | B19: NAICS CLASSIFICATION: (1114) | C19: 49857000
A20: AG SERVICES, OTHER - EXPENSE, MEASURED IN $ | B20: NAICS CLASSIFICATION: (1119) | C20: 184024000 | D20: =SUM(C16:C20) -> 416973000
A21: AG SERVICES, UTILITIES - EXPENSE, MEASURED IN $ | B21: NAICS CLASSIFICATION: (1111) | C21: 111738000
A22: AG SERVICES, UTILITIES - EXPENSE, MEASURED IN $ | B22: NAICS CLASSIFICATION: (1112) | C22: 25605000
A23: AG SERVICES, UTILITIES - EXPENSE, MEASURED IN $ | B23: NAICS CLASSIFICATION: (1113) | C23: 13959000
A24: AG SERVICES, UTILITIES - EXPENSE, MEASURED IN $ | B24: NAICS CLASSIFICATION: (1114) | C24: 32633000
A25: AG SERVICES, UTILITIES - EXPENSE, MEASURED IN $ | B25: NAICS CLASSIFICATION: (1119) | C25: 175212000 | D25: =SUM(C21:C25) -> 359147000
A26: ANIMAL TOTALS, (EXCL BREEDING) - EXPENSE, MEASURED IN $ | B26: NAICS CLASSIFICATION: (1111) | C26: 18618000
A27: ANIMAL TOTALS, (EXCL BREEDING) - EXPENSE, MEASURED IN $ | B27: NAICS CLASSIFICATION: (1112) | C27: 724000
A28: ANIMAL TOTALS, (EXCL BREEDING) - EXPENSE, MEASURED IN $ | B28: NAICS CLASSIFICATION: (1113) | C28: 558000
A29: ANIMAL TOTALS, (EXCL BREEDING) - EXPENSE, MEASURED IN $ | B29: NAICS CLASSIFICATION: (1114) | C29: 373000
A30: ANIMAL TOTALS, (EXCL BREEDING) - EXPENSE, MEASURED IN $ | B30: NAICS CLASSIFICATION: (1119) | C30: 16493000 | D30: =SUM(C26:C30) -> 36766000
A31: ANIMAL TOTALS, BREEDING - EXPENSE, MEASURED IN $ | B31: NAICS CLASSIFICATION: (1111) | C31: 8485000
A32: ANIMAL TOTALS, BREEDING - EXPENSE, MEASURED IN $ | B32: NAICS CLASSIFICATION: (1112) | C32: 916000
A33: ANIMAL TOTALS, BREEDING - EXPENSE, MEASURED IN $ | B33: NAICS CLASSIFICATION: (1113) | C33: 751000
A34: ANIMAL TOTALS, BREEDING - EXPENSE, MEASURED IN $ | B34: NAICS CLASSIFICATION: (1114) | C34: 483000
A35: ANIMAL TOTALS, BREEDING - EXPENSE, MEASURED IN $ | B35: NAICS CLASSIFICATION: (1119) | C35: 14925000 | D35: =SUM(C31:C35) -> 25560000
A36: CHEMICAL TOTALS - EXPENSE, MEASURED IN $ | B36: NAICS CLASSIFICATION: (1111) | C36: 275816000
A37: CHEMICAL TOTALS - EXPENSE, MEASURED IN $ | B37: NAICS CLASSIFICATION: (1112) | C37: 49618000
A38: CHEMICAL TOTALS - EXPENSE, MEASURED IN $ | B38: NAICS CLASSIFICATION: (1113) | C38: 21090000
A39: CHEMICAL TOTALS - EXPENSE, MEASURED IN $ | B39: NAICS CLASSIFICATION: (1114) | C39: 29390000
A40: CHEMICAL TOTALS - EXPENSE, MEASURED IN $ | B40: NAICS CLASSIFICATION: (1119) | C40: 348491000 | D40: =SUM(C36:C40) -> 724405000
A41: FEED - EXPENSE, MEASURED IN $ | B41: NAICS CLASSIFICATION: (1111) | C41: 28910000
A42: FEED - EXPENSE, MEASURED IN $ | B42: NAICS CLASSIFICATION: (1112) | C42: 5296000
A43: FEED - EXPENSE, MEASURED IN $ | B43: NAICS CLASSIFICATION: (1113) | C43: 6474000
A44: FEED - EXPENSE, MEASURED IN $ | B44: NAICS CLASSIFICATION: (1114) | C44: 3475000
A45: FEED - EXPENSE, MEASURED IN $ | B45: NAICS CLASSIFICATION: (1119) | C45: 55739000 | D45: =SUM(C41:C45) -> 99894000
A46: FERTILIZER TOTALS, INCL LIME & SOIL CONDITIONERS - EXPENSE, MEASURED IN $ | B46: NAICS CLASSIFICATION: (1111) | C46: 466451000
A47: FERTILIZER TOTALS, INCL LIME & SOIL CONDITIONERS - EXPENSE, MEASURED IN $ | B47: NAICS CLASSIFICATION: (1112) | C47: 64500000
A48: FERTILIZER TOTALS, INCL LIME & SOIL CONDITIONERS - EXPENSE, MEASURED IN $ | B48: NAICS CLASSIFICATION: (1113) | C48: 22845000
A49: FERTILIZER TOTALS, INCL LIME & SOIL CONDITIONERS - EXPENSE, MEASURED IN $ | B49: NAICS CLASSIFICATION: (1114) | C49: 56284000
A50: FERTILIZER TOTALS, INCL LIME & SOIL CONDITIONERS - EXPENSE, MEASURED IN $ | B50: NAICS CLASSIFICATION: (1119) | C50: 409958000 | D50: =SUM(C46:C50) -> 1020038000
A51: FUELS, INCL LUBRICANTS - EXPENSE, MEASURED IN $ | B51: NAICS CLASSIFICATION: (1111) | C51: 204346000
A52: FUELS, INCL LUBRICANTS - EXPENSE, MEASURED IN $ | B52: NAICS CLASSIFICATION: (1112) | C52: 35666000
A53: FUELS, INCL LUBRICANTS - EXPENSE, MEASURED IN $ | B53: NAICS CLASSIFICATION: (1113) | C53: 14471000
A54: FUELS, INCL LUBRICANTS - EXPENSE, MEASURED IN $ | B54: NAICS CLASSIFICATION: (1114) | C54: 45338000
A55: FUELS, INCL LUBRICANTS - EXPENSE, MEASURED IN $ | B55: NAICS CLASSIFICATION: (1119) | C55: 261926000 | D55: =SUM(C51:C55) -> 561747000
A56: INTEREST - EXPENSE, MEASURED IN $ | B56: NAICS CLASSIFICATION: (1111) | C56: 91229000
A57: INTEREST - EXPENSE, MEASURED IN $ | B57: NAICS CLASSIFICATION: (1112) | C57: 10935000
A58: INTEREST - EXPENSE, MEASURED IN $ | B58: NAICS CLASSIFICATION: (1113) | C58: 18396000
A59: INTEREST - EXPENSE, MEASURED IN $ | B59: NAICS CLASSIFICATION: (1114) | C59: 10393000
A60: INTEREST - EXPENSE, MEASURED IN $ | B60: NAICS CLASSIFICATION: (1119) | C60: 168390000 | D60: =SUM(C56:C60) -> 299343000
A61: LABOR, CONTRACT - EXPENSE, MEASURED IN $ | B61: NAICS CLASSIFICATION: (1111) | C61: 30971000
A62: LABOR, CONTRACT - EXPENSE, MEASURED IN $ | B62: NAICS CLASSIFICATION: (1112) | C62: 32951000
A63: LABOR, CONTRACT - EXPENSE, MEASURED IN $ | B63: NAICS CLASSIFICATION: (1113) | C63: 23645000
A64: LABOR, CONTRACT - EXPENSE, MEASURED IN $ | B64: NAICS CLASSIFICATION: (1114) | C64: 21202000
A65: LABOR, CONTRACT - EXPENSE, MEASURED IN $ | B65: NAICS CLASSIFICATION: (1119) | C65: 70127000 | D65: =SUM(C61:C65) -> 178896000
A66: LABOR, HIRED - EXPENSE, MEASURED IN $ | B66: NAICS CLASSIFICATION: (1111) | C66: 149627000
A67: LABOR, HIRED - EXPENSE, MEASURED IN $ | B67: NAICS CLASSIFICATION: (1112) | C67: 119863000
A68: LABOR, HIRED - EXPENSE, MEASURED IN $ | B68: NAICS CLASSIFICATION: (1113) | C68: 57160000
A69: LABOR, HIRED - EXPENSE, MEASURED IN $ | B69: NAICS CLASSIFICATION: (1114) | C69: 320081000
A70: LABOR, HIRED - EXPENSE, MEASURED IN $ | B70: NAICS CLASSIFICATION: (1119) | C70: 288743000 | D70: =SUM(C66:C70) -> 935474000
A71: RENT, CASH, LAND & BUILDINGS - EXPENSE, MEASURED IN $ | B71: NAICS CLASSIFICATION: (1111) | C71: 162434000
A72: RENT, CASH, LAND & BUILDINGS - EXPENSE, MEASURED IN $ | B72: NAICS CLASSIFICATION: (1112) | C72: 30924000
A73: RENT, CASH, LAND & BUILDINGS - EXPENSE, MEASURED IN $ | B73: NAICS CLASSIFICATION: (1113) | C73: 6220000
A74: RENT, CASH, LAND & BUILDINGS - EXPENSE, MEASURED IN $ | B74: NAICS CLASSIFICATION: (1114) | C74: 15333000
A75: RENT, CASH, LAND & BUILDINGS - EXPENSE, MEASURED IN $ | B75: NAICS CLASSIFICATION: (1119) | C75: 151184000 | D75: =SUM(C71:C75) -> 366095000
A76: SEEDS & PLANTS TOTALS - EXPENSE, MEASURED IN $ | B76: NAICS CLASSIFICATION: (1111) | C76: 276672000
A77: SEEDS & PLANTS TOTALS - EXPENSE, MEASURED IN $ | B77: NAICS CLASSIFICATION: (1112) | C77: 60548000
A78: SEEDS & PLANTS TOTALS - EXPENSE, MEASURED IN $ | B78: NAICS CLASSIFICATION: (1113) | C78: 7724000
A79: SEEDS & PLANTS TOTALS - EXPENSE, MEASURED IN $ | B79: NAICS CLASSIFICATION: (1114) | C79: 88446000
A80: SEEDS & PLANTS TOTALS - EXPENSE, MEASURED IN $ | B80: NAICS CLASSIFICATION: (1119) | C80: 323108000 | D80: =SUM(C76:C80) -> 756498000
A81: SUPPLIES & REPAIRS, (EXCL LUBRICANTS) - EXPENSE, MEASURED IN $ | B81: NAICS CLASSIFICATION: (1111) | C81: 222925000
A82: SUPPLIES & REPAIRS, (EXCL LUBRICANTS) - EXPENSE, MEASURED IN $ | B82: NAICS CLASSIFICATION: (1112) | C82: 46430000
A83: SUPPLIES & REPAIRS, (EXCL LUBRICANTS) - EXPENSE, MEASURED IN $ | B83: NAICS CLASSIFICATION: (1113) | C83: 26750000
A84: SUPPLIES & REPAIRS, (EXCL LUBRICANTS) - EXPENSE, MEASURED IN $ | B84: NAICS CLASSIFICATION: (1114) | C84: 55650000
A85: SUPPLIES & REPAIRS, (EXCL LUBRICANTS) - EXPENSE, MEASURED IN $ | B85: NAICS CLASSIFICATION: (1119) | C85: 340890000 | D85: =SUM(C81:C85) -> 692645000
A86: TAXES, PROPERTY, REAL ESTATE & NON-REAL ESTATE, (EXCL PAID BY LANDLORD) - EXPENSE, MEASURED IN $ | B86: NAICS CLASSIFICATION: (1111) | C86: 40933000
A87: TAXES, PROPERTY, REAL ESTATE & NON-REAL ESTATE, (EXCL PAID BY LANDLORD) - EXPENSE, MEASURED IN $ | B87: NAICS CLASSIFICATION: (1112) | C87: 7459000
A88: TAXES, PROPERTY, REAL ESTATE & NON-REAL ESTATE, (EXCL PAID BY LANDLORD) - EXPENSE, MEASURED IN $ | B88: NAICS CLASSIFICATION: (1113) | C88: 19918000
A89: TAXES, PROPERTY, REAL ESTATE & NON-REAL ESTATE, (EXCL PAID BY LANDLORD) - EXPENSE, MEASURED IN $ | B89: NAICS CLASSIFICATION: (1114) | C89: 11535000
A90: TAXES, PROPERTY, REAL ESTATE & NON-REAL ESTATE, (EXCL PAID BY LANDLORD) - EXPENSE, MEASURED IN $ | B90: NAICS CLASSIFICATION: (1119) | C90: 145391000 | D90: =SUM(C86:C90) -> 225236000
C92: =SUM(C1:C90) -> 7032100000
A103: SEEDS, FOR COVER CROPS - EXPENSE, MEASURED IN $ | B103: NAICS CLASSIFICATION: (1111) | C103: 4701000
A104: SEEDS, FOR COVER CROPS - EXPENSE, MEASURED IN $ | B104: NAICS CLASSIFICATION: (1112) | C104: 1047000
A105: SEEDS, FOR COVER CROPS - EXPENSE, MEASURED IN $ | B105: NAICS CLASSIFICATION: (1113) | C105: 197000
A106: SEEDS, FOR COVER CROPS - EXPENSE, MEASURED IN $ | B106: NAICS CLASSIFICATION: (1114) | C106: 106000
A107: SEEDS, FOR COVER CROPS - EXPENSE, MEASURED IN $ | B107: NAICS CLASSIFICATION: (1119) | C107: 10811000
A108: DEPRECIATION - EXPENSE, MEASURED IN $ | B108: NAICS CLASSIFICATION: (1111) | C108: 344454000
A109: DEPRECIATION - EXPENSE, MEASURED IN $ | B109: NAICS CLASSIFICATION: (1112) | C109: 51925000
A110: DEPRECIATION - EXPENSE, MEASURED IN $ | B110: NAICS CLASSIFICATION: (1113) | C110: 51505000
A111: DEPRECIATION - EXPENSE, MEASURED IN $ | B111: NAICS CLASSIFICATION: (1114) | C111: 64076000
...
